telelog/__init__.py
telelog/aaa.py
telelog/digital.py
telelog/utils.py
telelog-0.2.0.dist-info/METADATA
telelog-0.2.0.dist-info/WHEEL
telelog-0.2.0.dist-info/top_level.txt
telelog-0.2.0.dist-info/RECORD
