Metadata-Version: 2.1
Name: telelog
Version: 0.2.0
Summary: Python Package for le log toolkit
Home-page: UNKNOWN
Author: imason
Author-email: moy7@chinatelecom.cn
License: UNKNOWN
Keywords: python-log,telelog
Platform: UNKNOWN
Classifier: Programming Language :: Python :: 3
Classifier: License :: OSI Approved :: MIT License
Classifier: Operating System :: OS Independent
Requires-Python: >=3.6,
